framestructure/__init__.py
framestructure/arrayframe/__init__.py
framestructure/arrayframe/arraycontainer.py
framestructure/arrayframe/arrayframe.py
framestructure/arrayframe/arrayframeinterface.py
framestructure/arrayframe/blankarrayframe.py
framestructure/dataclasses/__init__.py
framestructure/directorytimeframe/__init__.py
framestructure/directorytimeframe/directorytimeframe.py
framestructure/directorytimeframe/directorytimeframeinterface.py
framestructure/filetimeframe/__init__.py
framestructure/filetimeframe/filetimecontainerinterface.py
framestructure/header.py
framestructure/py.typed
framestructure/timeaxisframe/__init__.py
framestructure/timeaxisframe/blanktimeaxisframe.py
framestructure/timeaxisframe/timeaxiscontainer.py
framestructure/timeaxisframe/timeaxisframe.py
framestructure/timeaxisframe/timeaxisframeinterface.py
framestructure/timeframe/__init__.py
framestructure/timeframe/blanktimeframe.py
framestructure/timeframe/timeframe.py
framestructure/timeframe/timeframeinterface.py
framestructure/timeseriesframe/__init__.py
framestructure/timeseriesframe/blanktimeseriesframe.py
framestructure/timeseriesframe/timeseriescontainer.py
framestructure/timeseriesframe/timeseriesframe.py
framestructure/timeseriesframe/timeseriesframeinterface.py
framestructure-0.4.1.dist-info/LICENSE.rst
framestructure-0.4.1.dist-info/METADATA
framestructure-0.4.1.dist-info/WHEEL
framestructure-0.4.1.dist-info/entry_points.txt
framestructure-0.4.1.dist-info/RECORD
