Metadata-Version: 2.1
Name: framestructure
Version: 0.4.1
Summary: Objects for organizing data in frame structures.
Home-page: https://github.com/FongAnthonyM/python-framestructure
License: MIT
Author: Anthony Fong
Author-email: FongAnthonyM@gmail.com
Requires-Python: >=3.10,<4.0
Classifier: Development Status :: 3 - Alpha
Classifier: License :: OSI Approved :: MIT License
Classifier: Programming Language :: Python :: 3
Classifier: Programming Language :: Python :: 3.10
Classifier: Programming Language :: Python :: 3.11
Requires-Dist: baseobjects (>=1.9.0,<2.0.0)
Requires-Dist: dspobjects (>=0.2.0,<0.3.0)
Requires-Dist: numpy (>=1.21.1,<2.0.0)
Requires-Dist: scipy (>=1.6.1,<2.0.0)
Project-URL: Changelog, https://github.com/FongAnthonyM/python-framestructure/releases
Project-URL: Documentation, https://python-framestructure.readthedocs.io
Project-URL: Repository, https://github.com/FongAnthonyM/python-framestructure
